{ "meteorite":
[{"name":"Aachen",
"recclass":"L5",
"mass":"21 g",
"year":"1880",
"x": 150,
"y": 150},

{"name":"Aarhus",
"recclass":"H6",
"mass":"720 g",
"year":"1951",
"x": 300,
"y": 150},

{"name":"Abee",
"recclass":"EH4",
"mass":"107000 g",
"year":"1952",
"x": 450,
"y": 150},

{"name":"Acapulco",
"recclass":"Acapulcoite",
"mass":"1,914 g",
"year":"1976",
"x": 150,
"y": 330},

{"name":"Achiras",
"recclass":"L6",
"mass":"780 g",
"year":"1902",
"x": 150,
"y": 240},

{"name":"Agen",
"recclass":"H5",
"mass":"30000 g",
"year":"1814",
"x": 300,
"y": 240},

{"name":"Hachi-oji",
"recclass":"H?",
"mass":"0.2 g",
"year":"1817",
"x": 450,
"y": 240},

{"name":"Haraiya",
"recclass":"Eucrite-mmict",
"mass":"1000 g",
"year":"1878",
"x": 300,
"y": 330},

{"name":"Sauguis",
"recclass":"L6",
"mass":"4000 g",
"year":"1868",
"x": 450,
"y": 330}
]
}
    